MANIFEST.in
README.rst
setup.py
django_selectable_filter.egg-info/PKG-INFO
django_selectable_filter.egg-info/SOURCES.txt
django_selectable_filter.egg-info/dependency_links.txt
django_selectable_filter.egg-info/not-zip-safe
django_selectable_filter.egg-info/requires.txt
django_selectable_filter.egg-info/top_level.txt
selectable_filter/__init__.py
selectable_filter/filter.py
selectable_filter/templates/selectable_filter/filter.html