Metadata-Version: 1.1
Name: django-selectable-filter
Version: 0.1.1
Summary: The filterspec to the Django administration that allow you to filter records using the resources of django-selectable library
Home-page: https://github.com/Gustavosdo/django-selectable-filter
Author: Gustavo Santana de Oliveira
Author-email: gustavo.sdo@gmail.com
License: MIT
Keywords: django admin,django filter selectable
Platform: UNKNOWN
Classifier: Development Status :: 4 - Beta
Classifier: Intended Audience :: Developers
Classifier: License :: OSI Approved :: MIT License
Classifier: Framework :: Django :: 1.7
Classifier: Programming Language :: Python :: 2.7
Classifier: Topic :: Software Development :: Libraries :: Python Modules
Classifier: Topic :: Internet :: WWW/HTTP :: WSGI
Classifier: Topic :: Software Development :: Libraries :: Application Frameworks
Classifier: Topic :: Internet :: WWW/HTTP :: Dynamic Content
Classifier: Environment :: Web Environment
Classifier: Operating System :: OS Independent
